README.md
setup.py
ldap_user/__init__.py
ldap_user/cli.py
ldap_user/config.py
ldap_user/user.py
ldap_user.egg-info/PKG-INFO
ldap_user.egg-info/SOURCES.txt
ldap_user.egg-info/dependency_links.txt
ldap_user.egg-info/entry_points.txt
ldap_user.egg-info/requires.txt
ldap_user.egg-info/top_level.txt
ldap_user/util/__init__.py
ldap_user/util/config.py
ldap_user/util/string_tool.py
ldap_user/util/verify_secret.py