Metadata-Version: 1.0
Name: ldap-user
Version: 0.5
Summary: use ldap verify user
Home-page: https://github.com/meisanggou/ldapuser
Author: meisanggou
Author-email: zhouheng@gene.ac
License: MIT
Keywords: ldap-user
Platform: UNKNOWN
